{
  "predictions": [
    {
      "ticker": "CMCT",
      "name": "Creative Media & Community Trust Corporation",
      "price3DaysAgo": 3.86,
      "priceToday": 6.68,
      "predictedMove": "+26% (Major Move)",
      "confidence": 95,
      "reasoning": "4.2x volume spike, Strong 73.1% gap, fresh news catalyst, low float, high short interest (51%), trending on social media",
      "keyFactors": [
        "Gap: 73.1%",
        "Volume: 4.2x",
        "Float: 0.6M",
        "Short: 51%",
        "News: 9"
      ],
      "news": " |  | \ud83d\udd25 Trending based on high_activity",
      "catalyst": "",
      "gap_percent": 73.1,
      "volume_ratio": 4.2,
      "float": 0.6,
      "short_percent": 50.7,
      "news_count": 9,
      "isPrediction": true,
      "learningWeights": {
        "gap_weight": 1.1,
        "volume_weight": 0.9,
        "news_weight": 0.9,
        "float_weight": 0.9,
        "short_weight": 0.9,
        "sentiment_weight": 1.0,
        "social_weight": 1.0
      },
      "tier": 1,
      "momentum_indicators": [],
      "social_score": 120,
      "is_trending": true,
      "red_flags": [
        "\u26a0\ufe0f Extreme gap - possible data error or halt",
        "Large move may have already occurred"
      ]
    },
    {
      "ticker": "ACXP",
      "name": "Acurx Pharmaceuticals, Inc.",
      "price3DaysAgo": 3.21,
      "priceToday": 4.43,
      "predictedMove": "+22% (Major Move)",
      "confidence": 95,
      "reasoning": "14.5x volume spike, Strong 38.0% gap, fresh news catalyst, low float, trending on social media",
      "keyFactors": [
        "Gap: 38.0%",
        "Volume: 14.5x",
        "Float: 2.0M",
        "News: 7"
      ],
      "news": " |  | \ud83d\udd25 Trending based on high_activity",
      "catalyst": "",
      "gap_percent": 38.0,
      "volume_ratio": 14.5,
      "float": 2.0,
      "short_percent": 1.8,
      "news_count": 7,
      "isPrediction": true,
      "learningWeights": {
        "gap_weight": 1.1,
        "volume_weight": 0.9,
        "news_weight": 0.9,
        "float_weight": 0.9,
        "short_weight": 0.9,
        "sentiment_weight": 1.0,
        "social_weight": 1.0
      },
      "tier": 1,
      "momentum_indicators": [],
      "social_score": 115,
      "is_trending": true,
      "red_flags": [
        "Large move may have already occurred"
      ]
    },
    {
      "ticker": "PRCH",
      "name": "Porch Group, Inc.",
      "price3DaysAgo": 9.36,
      "priceToday": 9.76,
      "predictedMove": "+7% (Moderate)",
      "confidence": 95,
      "reasoning": "fresh news catalyst, high short interest (23%)",
      "keyFactors": [
        "Gap: 4.3%",
        "Volume: 1.9x",
        "Float: 84.7M",
        "Short: 23%",
        "News: 10"
      ],
      "news": " | ",
      "catalyst": "",
      "gap_percent": 4.3,
      "volume_ratio": 1.9,
      "float": 84.7,
      "short_percent": 23.4,
      "news_count": 10,
      "isPrediction": true,
      "learningWeights": {
        "gap_weight": 1.1,
        "volume_weight": 0.9,
        "news_weight": 0.9,
        "float_weight": 0.9,
        "short_weight": 0.9,
        "sentiment_weight": 1.0,
        "social_weight": 1.0
      },
      "tier": 1,
      "momentum_indicators": [],
      "social_score": 15,
      "is_trending": false,
      "red_flags": []
    },
    {
      "ticker": "PHGE",
      "name": "BiomX Inc.",
      "price3DaysAgo": 5.17,
      "priceToday": 3.26,
      "predictedMove": "+19% (Strong)",
      "confidence": 95,
      "reasoning": "8.8x volume spike, fresh news catalyst, low float, trending on social media",
      "keyFactors": [
        "Gap: -36.9%",
        "Volume: 8.8x",
        "Float: 1.1M",
        "News: 5"
      ],
      "news": " |  | \ud83d\udd25 Trending based on high_activity",
      "catalyst": "",
      "gap_percent": -36.9,
      "volume_ratio": 8.8,
      "float": 1.1,
      "short_percent": 2.2,
      "news_count": 5,
      "isPrediction": true,
      "learningWeights": {
        "gap_weight": 1.1,
        "volume_weight": 0.9,
        "news_weight": 0.9,
        "float_weight": 0.9,
        "short_weight": 0.9,
        "sentiment_weight": 1.0,
        "social_weight": 1.0
      },
      "tier": 2,
      "momentum_indicators": [
        "news (5 articles)",
        "extreme volume (8.8x)",
        "accelerating volume (3 days)",
        "ultra-low float (1.1M)",
        "near 52-week low bounce"
      ],
      "social_score": 100,
      "is_trending": true,
      "red_flags": []
    },
    {
      "ticker": "MHUA",
      "name": "Meihua International Medical Technologies Co., Ltd.",
      "price3DaysAgo": 14.02,
      "priceToday": 7.61,
      "predictedMove": "+20% (Major Move)",
      "confidence": 95,
      "reasoning": "5.1x volume spike, fresh news catalyst, low float, trending on social media",
      "keyFactors": [
        "Gap: -45.7%",
        "Volume: 5.1x",
        "Float: 0.2M",
        "News: 5"
      ],
      "news": " |  | \ud83d\udd25 Trending based on high_activity",
      "catalyst": "",
      "gap_percent": -45.7,
      "volume_ratio": 5.1,
      "float": 0.2,
      "short_percent": 0.0,
      "news_count": 5,
      "isPrediction": true,
      "learningWeights": {
        "gap_weight": 1.1,
        "volume_weight": 0.9,
        "news_weight": 0.9,
        "float_weight": 0.9,
        "short_weight": 0.9,
        "sentiment_weight": 1.0,
        "social_weight": 1.0
      },
      "tier": 2,
      "momentum_indicators": [
        "news (5 articles)",
        "extreme volume (5.1x)",
        "accelerating volume (3 days)",
        "ultra-low float (0.2M)",
        "near 52-week low bounce"
      ],
      "social_score": 100,
      "is_trending": true,
      "red_flags": []
    },
    {
      "ticker": "GRI",
      "name": "GRI Bio, Inc.",
      "price3DaysAgo": 2.06,
      "priceToday": 1.35,
      "predictedMove": "+20% (Major Move)",
      "confidence": 95,
      "reasoning": "11.8x volume spike, fresh news catalyst, low float, trending on social media",
      "keyFactors": [
        "Gap: -34.5%",
        "Volume: 11.8x",
        "Float: 3.3M",
        "News: 3"
      ],
      "news": " |  | \ud83d\udd25 Trending based on high_activity",
      "catalyst": "",
      "gap_percent": -34.5,
      "volume_ratio": 11.8,
      "float": 3.3,
      "short_percent": 3.7,
      "news_count": 3,
      "isPrediction": true,
      "learningWeights": {
        "gap_weight": 1.1,
        "volume_weight": 0.9,
        "news_weight": 0.9,
        "float_weight": 0.9,
        "short_weight": 0.9,
        "sentiment_weight": 1.0,
        "social_weight": 1.0
      },
      "tier": 2,
      "momentum_indicators": [
        "news (3 articles)",
        "extreme volume (11.8x)",
        "accelerating volume (3 days)",
        "ultra-low float (3.3M)"
      ],
      "social_score": 115,
      "is_trending": true,
      "red_flags": []
    },
    {
      "ticker": "FUEMF",
      "name": "FUEMF",
      "price3DaysAgo": 4.13,
      "priceToday": 3.22,
      "predictedMove": "+8% (Moderate)",
      "confidence": 86.5,
      "reasoning": "4.1x volume spike, fresh news catalyst, trending on social media",
      "keyFactors": [
        "Gap: -22.2%",
        "Volume: 4.1x",
        "Float: 62.8M",
        "News: 10"
      ],
      "news": " |  | \ud83d\udd25 Trending based on moderate_activity",
      "catalyst": "",
      "gap_percent": -22.2,
      "volume_ratio": 4.1,
      "float": 62.8,
      "short_percent": 0,
      "news_count": 10,
      "isPrediction": true,
      "learningWeights": {
        "gap_weight": 1.1,
        "volume_weight": 0.9,
        "news_weight": 0.9,
        "float_weight": 0.9,
        "short_weight": 0.9,
        "sentiment_weight": 1.0,
        "social_weight": 1.0
      },
      "tier": 2,
      "momentum_indicators": [
        "news (10 articles)",
        "extreme volume (4.1x)"
      ],
      "social_score": 45,
      "is_trending": true,
      "red_flags": []
    },
    {
      "ticker": "IBIO",
      "name": "iBio, Inc.",
      "price3DaysAgo": 1.2,
      "priceToday": 1.67,
      "predictedMove": "+18% (Strong)",
      "confidence": 82.5,
      "reasoning": "\u26a0\ufe0f EXTREME 87.5x volume (SUSPICIOUS), Strong 39.2% gap, fresh news catalyst, trending on social media",
      "keyFactors": [
        "Gap: 39.2%",
        "Volume: 87.5x",
        "Float: 21.4M",
        "Short: 5%",
        "News: 7"
      ],
      "news": " |  | \ud83d\udd25 Trending based on high_activity",
      "catalyst": "",
      "gap_percent": 39.2,
      "volume_ratio": 87.5,
      "float": 21.4,
      "short_percent": 5.3,
      "news_count": 7,
      "isPrediction": true,
      "learningWeights": {
        "gap_weight": 1.1,
        "volume_weight": 0.9,
        "news_weight": 0.9,
        "float_weight": 0.9,
        "short_weight": 0.9,
        "sentiment_weight": 1.0,
        "social_weight": 1.0
      },
      "tier": 1,
      "momentum_indicators": [],
      "social_score": 70,
      "is_trending": true,
      "red_flags": [
        "Large move may have already occurred",
        "\u26a0\ufe0f EXTREME VOLUME - likely already moved or pump"
      ]
    },
    {
      "ticker": "LZMH",
      "name": "LZ Technology Holdings Limited",
      "price3DaysAgo": 2.41,
      "priceToday": 1.73,
      "predictedMove": "+11% (Strong)",
      "confidence": 76.5,
      "reasoning": "fresh news catalyst, low float, trending on social media",
      "keyFactors": [
        "Gap: -28.2%",
        "Volume: 1.5x",
        "Float: 4.9M",
        "News: 4"
      ],
      "news": " |  | \ud83d\udd25 Trending based on moderate_activity",
      "catalyst": "",
      "gap_percent": -28.2,
      "volume_ratio": 1.5,
      "float": 4.9,
      "short_percent": 1.1,
      "news_count": 4,
      "isPrediction": true,
      "learningWeights": {
        "gap_weight": 1.1,
        "volume_weight": 0.9,
        "news_weight": 0.9,
        "float_weight": 0.9,
        "short_weight": 0.9,
        "sentiment_weight": 1.0,
        "social_weight": 1.0
      },
      "tier": 2,
      "momentum_indicators": [
        "news (4 articles)",
        "ultra-low float (4.9M)",
        "micro-cap (263M)",
        "near 52-week low bounce"
      ],
      "social_score": 30,
      "is_trending": true,
      "red_flags": []
    },
    {
      "ticker": "TWMIF",
      "name": "Tidewater Midstream and Infrastructure Ltd.",
      "price3DaysAgo": 3.46,
      "priceToday": 3.5,
      "predictedMove": "+1%",
      "confidence": 76.5,
      "reasoning": "elevated volume, fresh news catalyst, low float",
      "keyFactors": [
        "Gap: 1.0%",
        "Volume: 2.4x",
        "Float: 11.8M",
        "News: 10"
      ],
      "news": " | ",
      "catalyst": "",
      "gap_percent": 1.0,
      "volume_ratio": 2.4,
      "float": 11.8,
      "short_percent": 0,
      "news_count": 10,
      "isPrediction": true,
      "learningWeights": {
        "gap_weight": 1.1,
        "volume_weight": 0.9,
        "news_weight": 0.9,
        "float_weight": 0.9,
        "short_weight": 0.9,
        "sentiment_weight": 1.0,
        "social_weight": 1.0
      },
      "tier": 2,
      "momentum_indicators": [
        "news (10 articles)",
        "micro-cap (75M)"
      ],
      "social_score": 10,
      "is_trending": false,
      "red_flags": []
    }
  ],
  "generatedTime": "2025-12-09 01:38 AM",
  "targetDate": "2025-12-09",
  "tradingStyle": "DAY_TRADING",
  "learningSystem": {
    "enabled": true,
    "historicalPredictions": 90,
    "weights": {
      "gap_weight": 1.1,
      "volume_weight": 0.9,
      "news_weight": 0.9,
      "float_weight": 0.9,
      "short_weight": 0.9,
      "sentiment_weight": 1.0,
      "social_weight": 1.0
    },
    "insights": {
      "best_gap_range": {
        "range": "High (10-20%)",
        "accuracy": 100.0
      },
      "recent_trend": 0.0,
      "confidence_adjustment": -5,
      "weights_updated": true
    }
  },
  "enhancements": {
    "socialMediaScanning": true,
    "twoTierFiltering": true,
    "trapAvoidance": true,
    "newsQualityScoring": true,
    "dynamicScreeners": true,
    "dataValidation": true,
    "extremeVolumeDetection": true
  }
}