{
  "history": [
    {
      "ticker": "WOK",
      "name": "WORK Medical Technology Group LTD",
      "predictedPrice": 6.66,
      "actualPrice": 11.66,
      "predictedMove": "+19% (Strong)",
      "actualMove": "+75.1%",
      "wasCorrect": false,
      "status": "PARTIAL",
      "confidence": 93,
      "reasoning": "Strong 69.9% gap, fresh news catalyst, low float, trending on social media",
      "keyFactors": [
        "Gap: 69.9%",
        "Volume: 1.8x",
        "Float: 1.2M",
        "Short: 5%",
        "News: 14"
      ],
      "predictionDate": "2026-05-13",
      "targetDate": "2026-05-13",
      "checkDate": "2026-05-14",
      "priceType": "Pre-Market High (4:00-9:59 AM EST)",
      "gap_percent": 69.9,
      "volume_ratio": 1.8,
      "float": 1.2,
      "short_percent": 5.4,
      "news_count": 14
    },
    {
      "ticker": "GTM",
      "name": "ZoomInfo Technologies Inc.",
      "predictedPrice": 4.06,
      "actualPrice": 4.08,
      "predictedMove": "+10% (Strong)",
      "actualMove": "+0.5%",
      "wasCorrect": false,
      "status": "PARTIAL",
      "confidence": 92,
      "reasoning": "elevated volume, fresh news catalyst, high short interest (15%), trending on social media",
      "keyFactors": [
        "Gap: -32.8%",
        "Volume: 2.9x",
        "Float: 229.6M",
        "Short: 15%",
        "News: 20"
      ],
      "predictionDate": "2026-05-13",
      "targetDate": "2026-05-13",
      "checkDate": "2026-05-14",
      "priceType": "Pre-Market High (4:00-9:59 AM EST)",
      "gap_percent": -32.8,
      "volume_ratio": 2.9,
      "float": 229.6,
      "short_percent": 15.2,
      "news_count": 20
    },
    {
      "ticker": "REPL",
      "name": "Replimune Group, Inc.",
      "predictedPrice": 5.3,
      "actualPrice": 5.53,
      "predictedMove": "+14% (Strong)",
      "actualMove": "+4.4%",
      "wasCorrect": false,
      "status": "PARTIAL",
      "confidence": 95,
      "reasoning": "elevated volume, Strong 29.6% gap, fresh news catalyst, high short interest (46%), trending on social media",
      "keyFactors": [
        "Gap: 29.6%",
        "Volume: 2.0x",
        "Float: 62.9M",
        "Short: 46%",
        "News: 15"
      ],
      "predictionDate": "2026-05-14",
      "targetDate": "2026-05-14",
      "checkDate": "2026-05-15",
      "priceType": "Pre-Market High (4:00-9:59 AM EST)",
      "gap_percent": 29.6,
      "volume_ratio": 2.0,
      "float": 62.9,
      "short_percent": 45.9,
      "news_count": 15
    },
    {
      "ticker": "BTM",
      "name": "Bitcoin Depot Inc.",
      "predictedPrice": 2.62,
      "actualPrice": 3.0,
      "predictedMove": "+19% (Strong)",
      "actualMove": "+14.5%",
      "wasCorrect": true,
      "status": "PERFECT",
      "confidence": 95,
      "reasoning": "4.5x volume spike, fresh news catalyst, low float, trending on social media",
      "keyFactors": [
        "Gap: -43.7%",
        "Volume: 4.5x",
        "Float: 5.2M",
        "Short: 6%",
        "News: 16"
      ],
      "predictionDate": "2026-05-14",
      "targetDate": "2026-05-14",
      "checkDate": "2026-05-15",
      "priceType": "Pre-Market High (4:00-9:59 AM EST)",
      "gap_percent": -43.7,
      "volume_ratio": 4.5,
      "float": 5.2,
      "short_percent": 5.7,
      "news_count": 16
    },
    {
      "ticker": "TUSK",
      "name": "Mammoth Energy Services, Inc.",
      "predictedPrice": 3.26,
      "actualPrice": 3.45,
      "predictedMove": "+5%",
      "actualMove": "+5.8%",
      "wasCorrect": false,
      "status": "PARTIAL",
      "confidence": 95,
      "reasoning": "3.4x volume spike, Strong 10.9% gap, fresh news catalyst, trending on social media",
      "keyFactors": [
        "Gap: 10.9%",
        "Volume: 3.4x",
        "Float: 42.5M",
        "News: 10"
      ],
      "predictionDate": "2026-05-14",
      "targetDate": "2026-05-14",
      "checkDate": "2026-05-15",
      "priceType": "Pre-Market High (4:00-9:59 AM EST)",
      "gap_percent": 10.9,
      "volume_ratio": 3.4,
      "float": 42.5,
      "short_percent": 3.5,
      "news_count": 10
    },
    {
      "ticker": "BRCB",
      "name": "Black Rock Coffee Bar, Inc.",
      "predictedPrice": 7.65,
      "actualPrice": 8.08,
      "predictedMove": "+13% (Strong)",
      "actualMove": "+5.6%",
      "wasCorrect": false,
      "status": "PARTIAL",
      "confidence": 95,
      "reasoning": "9.3x volume spike, fresh news catalyst, low float, trending on social media",
      "keyFactors": [
        "Gap: -30.3%",
        "Volume: 9.3x",
        "Float: 16.6M",
        "Short: 11%",
        "News: 20"
      ],
      "predictionDate": "2026-05-14",
      "targetDate": "2026-05-14",
      "checkDate": "2026-05-15",
      "priceType": "Pre-Market High (4:00-9:59 AM EST)",
      "gap_percent": -30.3,
      "volume_ratio": 9.3,
      "float": 16.6,
      "short_percent": 10.5,
      "news_count": 20
    },
    {
      "ticker": "WOK",
      "name": "WORK Medical Technology Group LTD",
      "predictedPrice": 2.76,
      "actualPrice": 2.54,
      "predictedMove": "+21% (Major Move)",
      "actualMove": "-8.0%",
      "wasCorrect": false,
      "status": "WRONG",
      "confidence": 95,
      "reasoning": "3.3x volume spike, fresh news catalyst, low float, trending on social media",
      "keyFactors": [
        "Gap: -58.6%",
        "Volume: 3.3x",
        "Float: 1.2M",
        "Short: 5%",
        "News: 15"
      ],
      "predictionDate": "2026-05-14",
      "targetDate": "2026-05-14",
      "checkDate": "2026-05-15",
      "priceType": "Pre-Market High (4:00-9:59 AM EST)",
      "gap_percent": -58.6,
      "volume_ratio": 3.3,
      "float": 1.2,
      "short_percent": 5.4,
      "news_count": 15
    },
    {
      "ticker": "PLUG",
      "name": "Plug Power Inc.",
      "predictedPrice": 3.96,
      "actualPrice": 3.99,
      "predictedMove": "+9% (Moderate)",
      "actualMove": "+0.8%",
      "wasCorrect": false,
      "status": "PARTIAL",
      "confidence": 95,
      "reasoning": "Strong 11.2% gap, fresh news catalyst, high short interest (28%), trending on social media",
      "keyFactors": [
        "Gap: 11.2%",
        "Volume: 1.3x",
        "Float: 1330.6M",
        "Short: 28%",
        "News: 20"
      ],
      "predictionDate": "2026-05-14",
      "targetDate": "2026-05-14",
      "checkDate": "2026-05-15",
      "priceType": "Pre-Market High (4:00-9:59 AM EST)",
      "gap_percent": 11.2,
      "volume_ratio": 1.3,
      "float": 1330.6,
      "short_percent": 27.8,
      "news_count": 20
    },
    {
      "ticker": "IDN",
      "name": "Intellicheck, Inc.",
      "predictedPrice": 4.45,
      "actualPrice": 4.78,
      "predictedMove": "+16% (Strong)",
      "actualMove": "+7.4%",
      "wasCorrect": false,
      "status": "PARTIAL",
      "confidence": 95,
      "reasoning": "11.6x volume spike, fresh news catalyst, low float, trending on social media",
      "keyFactors": [
        "Gap: -38.4%",
        "Volume: 11.6x",
        "Float: 17.7M",
        "News: 20"
      ],
      "predictionDate": "2026-05-14",
      "targetDate": "2026-05-14",
      "checkDate": "2026-05-15",
      "priceType": "Pre-Market High (4:00-9:59 AM EST)",
      "gap_percent": -38.4,
      "volume_ratio": 11.6,
      "float": 17.7,
      "short_percent": 2.0,
      "news_count": 20
    },
    {
      "ticker": "SBFM",
      "name": "Sunshine Biopharma, Inc.",
      "predictedPrice": 0.66,
      "actualPrice": 0.65,
      "predictedMove": "+15% (Strong)",
      "actualMove": "-1.5%",
      "wasCorrect": false,
      "status": "WRONG",
      "confidence": 86,
      "reasoning": "elevated volume, fresh news catalyst, low float, trending on social media",
      "keyFactors": [
        "Gap: -37.1%",
        "Volume: 2.6x",
        "Float: 4.8M",
        "News: 4"
      ],
      "predictionDate": "2026-05-14",
      "targetDate": "2026-05-14",
      "checkDate": "2026-05-15",
      "priceType": "Pre-Market High (4:00-9:59 AM EST)",
      "gap_percent": -37.1,
      "volume_ratio": 2.6,
      "float": 4.8,
      "short_percent": 2.1,
      "news_count": 4
    },
    {
      "ticker": "FCHL",
      "name": "Fitness Champs Holdings Limited",
      "predictedPrice": 2.03,
      "actualPrice": 2.15,
      "predictedMove": "+25% (Major Move)",
      "actualMove": "+5.9%",
      "wasCorrect": false,
      "status": "PARTIAL",
      "confidence": 82,
      "reasoning": "\u26a0\ufe0f Very high 41.2x volume, Strong 52.6% gap, fresh news catalyst, low float, trending on social media",
      "keyFactors": [
        "Gap: 52.6%",
        "Volume: 41.2x",
        "Float: 6.3M",
        "News: 17"
      ],
      "predictionDate": "2026-05-14",
      "targetDate": "2026-05-14",
      "checkDate": "2026-05-15",
      "priceType": "Pre-Market High (4:00-9:59 AM EST)",
      "gap_percent": 52.6,
      "volume_ratio": 41.2,
      "float": 6.3,
      "short_percent": 3.3,
      "news_count": 17
    },
    {
      "ticker": "PSTV",
      "name": "Plus Therapeutics, Inc.",
      "predictedPrice": 5.84,
      "actualPrice": 6.25,
      "predictedMove": "+9% (Moderate)",
      "actualMove": "+7.0%",
      "wasCorrect": false,
      "status": "PARTIAL",
      "confidence": 95,
      "reasoning": "elevated volume, Strong 11.2% gap, fresh news catalyst, low float, high short interest (18%), trending on social media",
      "keyFactors": [
        "Gap: 11.2%",
        "Volume: 2.0x",
        "Float: 6.3M",
        "Short: 18%",
        "News: 10"
      ],
      "predictionDate": "2026-05-19",
      "targetDate": "2026-05-19",
      "checkDate": "2026-05-20",
      "priceType": "Pre-Market High (4:00-9:59 AM EST)",
      "gap_percent": 11.2,
      "volume_ratio": 2.0,
      "float": 6.3,
      "short_percent": 18.0,
      "news_count": 10
    },
    {
      "ticker": "BTM",
      "name": "Bitcoin Depot Inc.",
      "predictedPrice": 0.78,
      "actualPrice": 0.72,
      "predictedMove": "+23% (Major Move)",
      "actualMove": "-7.7%",
      "wasCorrect": false,
      "status": "WRONG",
      "confidence": 95,
      "reasoning": "9.3x volume spike, fresh news catalyst, low float, trending on social media",
      "keyFactors": [
        "Gap: -73.2%",
        "Volume: 9.3x",
        "Float: 5.2M",
        "Short: 6%",
        "News: 20"
      ],
      "predictionDate": "2026-05-19",
      "targetDate": "2026-05-19",
      "checkDate": "2026-05-20",
      "priceType": "Pre-Market High (4:00-9:59 AM EST)",
      "gap_percent": -73.2,
      "volume_ratio": 9.3,
      "float": 5.2,
      "short_percent": 5.7,
      "news_count": 20
    },
    {
      "ticker": "HIVE",
      "name": "HIVE Digital Technologies Ltd.",
      "predictedPrice": 3.46,
      "actualPrice": 3.61,
      "predictedMove": "+12% (Strong)",
      "actualMove": "+4.3%",
      "wasCorrect": false,
      "status": "PARTIAL",
      "confidence": 95,
      "reasoning": "8.1x volume spike, Strong 28.6% gap, fresh news catalyst, trending on social media",
      "keyFactors": [
        "Gap: 28.6%",
        "Volume: 8.1x",
        "Float: 238.0M",
        "News: 17"
      ],
      "predictionDate": "2026-05-19",
      "targetDate": "2026-05-19",
      "checkDate": "2026-05-20",
      "priceType": "Pre-Market High (4:00-9:59 AM EST)",
      "gap_percent": 28.6,
      "volume_ratio": 8.1,
      "float": 238.0,
      "short_percent": 0.0,
      "news_count": 17
    },
    {
      "ticker": "NEOV",
      "name": "NeoVolta Inc.",
      "predictedPrice": 1.6,
      "actualPrice": 2.15,
      "predictedMove": "+15% (Strong)",
      "actualMove": "+34.3%",
      "wasCorrect": false,
      "status": "PARTIAL",
      "confidence": 95,
      "reasoning": "8.4x volume spike, fresh news catalyst, trending on social media",
      "keyFactors": [
        "Gap: -37.5%",
        "Volume: 8.4x",
        "Float: 36.0M",
        "Short: 9%",
        "News: 12"
      ],
      "predictionDate": "2026-05-19",
      "targetDate": "2026-05-19",
      "checkDate": "2026-05-20",
      "priceType": "Pre-Market High (4:00-9:59 AM EST)",
      "gap_percent": -37.5,
      "volume_ratio": 8.4,
      "float": 36.0,
      "short_percent": 9.3,
      "news_count": 12
    },
    {
      "ticker": "EDSA",
      "name": "EDSA",
      "predictedPrice": 9.0,
      "actualPrice": 11.32,
      "predictedMove": "+15% (Strong)",
      "actualMove": "+25.7%",
      "wasCorrect": false,
      "status": "PARTIAL",
      "confidence": 95,
      "reasoning": "elevated volume, fresh news catalyst, low float, trending on social media",
      "keyFactors": [
        "Gap: -31.0%",
        "Volume: 2.7x",
        "Float: 3.9M",
        "Short: 6%",
        "News: 5"
      ],
      "predictionDate": "2026-05-19",
      "targetDate": "2026-05-19",
      "checkDate": "2026-05-20",
      "priceType": "Pre-Market High (4:00-9:59 AM EST)",
      "gap_percent": -31.0,
      "volume_ratio": 2.7,
      "float": 3.9,
      "short_percent": 6.3,
      "news_count": 5
    },
    {
      "ticker": "PMEC",
      "name": "Primech Holdings Ltd.",
      "predictedPrice": 0.79,
      "actualPrice": 0.8,
      "predictedMove": "+6% (Moderate)",
      "actualMove": "+0.6%",
      "wasCorrect": false,
      "status": "PARTIAL",
      "confidence": 92,
      "reasoning": "fresh news catalyst, low float",
      "keyFactors": [
        "Gap: 3.9%",
        "Volume: 1.3x",
        "Float: 5.5M",
        "Short: 6%",
        "News: 3"
      ],
      "predictionDate": "2026-05-19",
      "targetDate": "2026-05-19",
      "checkDate": "2026-05-20",
      "priceType": "Pre-Market High (4:00-9:59 AM EST)",
      "gap_percent": 3.9,
      "volume_ratio": 1.3,
      "float": 5.5,
      "short_percent": 6.2,
      "news_count": 3
    },
    {
      "ticker": "LICN",
      "name": "Lichen International Limited",
      "predictedPrice": 3.77,
      "actualPrice": 4.65,
      "predictedMove": "+15% (Strong)",
      "actualMove": "+23.4%",
      "wasCorrect": false,
      "status": "PARTIAL",
      "confidence": 90,
      "reasoning": "5.5x volume spike, fresh news catalyst, low float, trending on social media",
      "keyFactors": [
        "Gap: -46.8%",
        "Volume: 5.5x",
        "Float: 16.3M",
        "News: 1"
      ],
      "predictionDate": "2026-05-19",
      "targetDate": "2026-05-19",
      "checkDate": "2026-05-20",
      "priceType": "Pre-Market High (4:00-9:59 AM EST)",
      "gap_percent": -46.8,
      "volume_ratio": 5.5,
      "float": 16.3,
      "short_percent": 0.0,
      "news_count": 1
    },
    {
      "ticker": "INDP",
      "name": "Indaptus Therapeutics, Inc.",
      "predictedPrice": 1.52,
      "actualPrice": 1.61,
      "predictedMove": "+6% (Moderate)",
      "actualMove": "+5.9%",
      "wasCorrect": false,
      "status": "PARTIAL",
      "confidence": 86,
      "reasoning": "fresh news catalyst, low float",
      "keyFactors": [
        "Gap: -4.4%",
        "Volume: 1.9x",
        "Float: 2.2M",
        "Short: 11%",
        "News: 1"
      ],
      "predictionDate": "2026-05-19",
      "targetDate": "2026-05-19",
      "checkDate": "2026-05-20",
      "priceType": "Pre-Market High (4:00-9:59 AM EST)",
      "gap_percent": -4.4,
      "volume_ratio": 1.9,
      "float": 2.2,
      "short_percent": 11.2,
      "news_count": 1
    },
    {
      "ticker": "SPDN",
      "name": "Direxion Daily S&P 500 Bear 1X Shares",
      "predictedPrice": 8.82,
      "actualPrice": 8.88,
      "predictedMove": "+1%",
      "actualMove": "+0.7%",
      "wasCorrect": false,
      "status": "PARTIAL",
      "confidence": 64,
      "reasoning": "elevated volume, fresh news catalyst",
      "keyFactors": [
        "Gap: 0.2%",
        "Volume: 2.1x",
        "Float: 1000.0M",
        "News: 3"
      ],
      "predictionDate": "2026-05-19",
      "targetDate": "2026-05-19",
      "checkDate": "2026-05-20",
      "priceType": "Pre-Market High (4:00-9:59 AM EST)",
      "gap_percent": 0.2,
      "volume_ratio": 2.1,
      "float": 1000.0,
      "short_percent": 0.0,
      "news_count": 3
    },
    {
      "ticker": "TZA",
      "name": "Direxion Daily Small Cap Bear 3X Shares",
      "predictedPrice": 5.05,
      "actualPrice": 5.29,
      "predictedMove": "+1%",
      "actualMove": "+4.8%",
      "wasCorrect": false,
      "status": "PARTIAL",
      "confidence": 49,
      "reasoning": "fresh news catalyst",
      "keyFactors": [
        "Gap: 1.8%",
        "Volume: 1.2x",
        "Float: 1000.0M",
        "News: 2"
      ],
      "predictionDate": "2026-05-19",
      "targetDate": "2026-05-19",
      "checkDate": "2026-05-20",
      "priceType": "Pre-Market High (4:00-9:59 AM EST)",
      "gap_percent": 1.8,
      "volume_ratio": 1.2,
      "float": 1000.0,
      "short_percent": 0.0,
      "news_count": 2
    },
    {
      "ticker": "LVO",
      "name": "LiveOne, Inc.",
      "predictedPrice": 6.51,
      "actualPrice": 6.66,
      "predictedMove": "+6% (Moderate)",
      "actualMove": "+2.3%",
      "wasCorrect": false,
      "status": "PARTIAL",
      "confidence": 89,
      "reasoning": "fresh news catalyst, low float",
      "keyFactors": [
        "Gap: 4.7%",
        "Volume: 1.3x",
        "Float: 9.6M",
        "News: 13"
      ],
      "predictionDate": "2026-05-20",
      "targetDate": "2026-05-20",
      "checkDate": "2026-05-21",
      "priceType": "Pre-Market High (4:00-9:59 AM EST)",
      "gap_percent": 4.7,
      "volume_ratio": 1.3,
      "float": 9.6,
      "short_percent": 1.7,
      "news_count": 13
    },
    {
      "ticker": "JYD",
      "name": "Jayud Global Logistics Limited",
      "predictedPrice": 1.88,
      "actualPrice": 2.99,
      "predictedMove": "+22% (Major Move)",
      "actualMove": "+59.2%",
      "wasCorrect": false,
      "status": "PARTIAL",
      "confidence": 72,
      "reasoning": "\u26a0\ufe0f Very high 44.4x volume, fresh news catalyst, low float, trending on social media",
      "keyFactors": [
        "Gap: -65.9%",
        "Volume: 44.4x",
        "Float: 2.6M",
        "News: 6"
      ],
      "predictionDate": "2026-05-20",
      "targetDate": "2026-05-20",
      "checkDate": "2026-05-21",
      "priceType": "Pre-Market High (4:00-9:59 AM EST)",
      "gap_percent": -65.9,
      "volume_ratio": 44.4,
      "float": 2.6,
      "short_percent": 0.3,
      "news_count": 6
    },
    {
      "ticker": "SOXS",
      "name": "Direxion Daily Semiconductor Bear 3X Shares",
      "predictedPrice": 9.93,
      "actualPrice": 10.0,
      "predictedMove": "+1%",
      "actualMove": "+0.7%",
      "wasCorrect": false,
      "status": "PARTIAL",
      "confidence": 63,
      "reasoning": "fresh news catalyst",
      "keyFactors": [
        "Gap: -0.2%",
        "Volume: 1.5x",
        "Float: 1000.0M",
        "News: 10"
      ],
      "predictionDate": "2026-05-20",
      "targetDate": "2026-05-20",
      "checkDate": "2026-05-21",
      "priceType": "Pre-Market High (4:00-9:59 AM EST)",
      "gap_percent": -0.2,
      "volume_ratio": 1.5,
      "float": 1000.0,
      "short_percent": 0.0,
      "news_count": 10
    },
    {
      "ticker": "DETX",
      "name": "Liberty Defense Holdings, Ltd.",
      "predictedPrice": 3.86,
      "actualPrice": 4.01,
      "predictedMove": "+4%",
      "actualMove": "+3.8%",
      "wasCorrect": false,
      "status": "PARTIAL",
      "confidence": 62,
      "reasoning": "low float",
      "keyFactors": [
        "Gap: -4.9%",
        "Volume: 1.3x",
        "Float: 1.5M"
      ],
      "predictionDate": "2026-05-20",
      "targetDate": "2026-05-20",
      "checkDate": "2026-05-21",
      "priceType": "Pre-Market High (4:00-9:59 AM EST)",
      "gap_percent": -4.9,
      "volume_ratio": 1.3,
      "float": 1.5,
      "short_percent": 0.0,
      "news_count": 0
    },
    {
      "ticker": "TZA",
      "name": "Direxion Daily Small Cap Bear 3X Shares",
      "predictedPrice": 5.21,
      "actualPrice": 5.26,
      "predictedMove": "+1%",
      "actualMove": "+1.0%",
      "wasCorrect": false,
      "status": "PARTIAL",
      "confidence": 53,
      "reasoning": "fresh news catalyst",
      "keyFactors": [
        "Gap: 3.2%",
        "Volume: 1.4x",
        "Float: 1000.0M",
        "News: 2"
      ],
      "predictionDate": "2026-05-20",
      "targetDate": "2026-05-20",
      "checkDate": "2026-05-21",
      "priceType": "Pre-Market High (4:00-9:59 AM EST)",
      "gap_percent": 3.2,
      "volume_ratio": 1.4,
      "float": 1000.0,
      "short_percent": 0.0,
      "news_count": 2
    },
    {
      "ticker": "MTVA",
      "name": "MetaVia Inc.",
      "predictedPrice": 2.89,
      "actualPrice": 2.95,
      "predictedMove": "+20% (Major Move)",
      "actualMove": "+2.1%",
      "wasCorrect": false,
      "status": "PARTIAL",
      "confidence": 95,
      "reasoning": "elevated volume, Strong 53.7% gap, fresh news catalyst, low float, trending on social media",
      "keyFactors": [
        "Gap: 53.7%",
        "Volume: 2.8x",
        "Float: 3.4M",
        "News: 13"
      ],
      "predictionDate": "2026-05-21",
      "targetDate": "2026-05-21",
      "checkDate": "2026-05-22",
      "priceType": "Pre-Market High (4:00-9:59 AM EST)",
      "gap_percent": 53.7,
      "volume_ratio": 2.8,
      "float": 3.4,
      "short_percent": 2.4,
      "news_count": 13
    },
    {
      "ticker": "TE",
      "name": "T1 Energy Inc.",
      "predictedPrice": 8.7,
      "actualPrice": 9.7,
      "predictedMove": "+13% (Strong)",
      "actualMove": "+11.5%",
      "wasCorrect": true,
      "status": "PERFECT",
      "confidence": 95,
      "reasoning": "elevated volume, Strong 26.5% gap, fresh news catalyst, high short interest (21%), trending on social media",
      "keyFactors": [
        "Gap: 26.5%",
        "Volume: 2.2x",
        "Float: 172.6M",
        "Short: 21%",
        "News: 18"
      ],
      "predictionDate": "2026-05-21",
      "targetDate": "2026-05-21",
      "checkDate": "2026-05-22",
      "priceType": "Pre-Market High (4:00-9:59 AM EST)",
      "gap_percent": 26.5,
      "volume_ratio": 2.2,
      "float": 172.6,
      "short_percent": 21.3,
      "news_count": 18
    },
    {
      "ticker": "MLGO",
      "name": "MicroAlgo Inc.",
      "predictedPrice": 5.36,
      "actualPrice": 5.95,
      "predictedMove": "+13% (Strong)",
      "actualMove": "+11.0%",
      "wasCorrect": true,
      "status": "PERFECT",
      "confidence": 95,
      "reasoning": "3.6x volume spike, Strong 39.9% gap, fresh news catalyst, low float, trending on social media",
      "keyFactors": [
        "Gap: 39.9%",
        "Volume: 3.6x",
        "Float: 10.9M",
        "Short: 15%",
        "News: 6"
      ],
      "predictionDate": "2026-05-21",
      "targetDate": "2026-05-21",
      "checkDate": "2026-05-22",
      "priceType": "Pre-Market High (4:00-9:59 AM EST)",
      "gap_percent": 39.9,
      "volume_ratio": 3.6,
      "float": 10.9,
      "short_percent": 14.7,
      "news_count": 6
    },
    {
      "ticker": "BNZI",
      "name": "Banzai International, Inc.",
      "predictedPrice": 3.54,
      "actualPrice": 4.01,
      "predictedMove": "+14% (Strong)",
      "actualMove": "+13.3%",
      "wasCorrect": true,
      "status": "PERFECT",
      "confidence": 95,
      "reasoning": "14.9x volume spike, fresh news catalyst, low float, trending on social media",
      "keyFactors": [
        "Gap: -7.1%",
        "Volume: 14.9x",
        "Float: 1.4M",
        "Short: 8%",
        "News: 15"
      ],
      "predictionDate": "2026-05-21",
      "targetDate": "2026-05-21",
      "checkDate": "2026-05-22",
      "priceType": "Pre-Market High (4:00-9:59 AM EST)",
      "gap_percent": -7.1,
      "volume_ratio": 14.9,
      "float": 1.4,
      "short_percent": 8.2,
      "news_count": 15
    },
    {
      "ticker": "GCL",
      "name": "GCL Global Holdings Ltd",
      "predictedPrice": 0.74,
      "actualPrice": 0.78,
      "predictedMove": "+20% (Major Move)",
      "actualMove": "+5.7%",
      "wasCorrect": false,
      "status": "PARTIAL",
      "confidence": 95,
      "reasoning": "13.0x volume spike, Strong 72.3% gap, fresh news catalyst, trending on social media",
      "keyFactors": [
        "Gap: 72.3%",
        "Volume: 13.0x",
        "Float: 33.5M",
        "News: 14"
      ],
      "predictionDate": "2026-05-21",
      "targetDate": "2026-05-21",
      "checkDate": "2026-05-22",
      "priceType": "Pre-Market High (4:00-9:59 AM EST)",
      "gap_percent": 72.3,
      "volume_ratio": 13.0,
      "float": 33.5,
      "short_percent": 0.2,
      "news_count": 14
    },
    {
      "ticker": "JYD",
      "name": "Jayud Global Logistics Limited",
      "predictedPrice": 0.9,
      "actualPrice": 0.94,
      "predictedMove": "+21% (Major Move)",
      "actualMove": "+4.5%",
      "wasCorrect": false,
      "status": "PARTIAL",
      "confidence": 95,
      "reasoning": "4.8x volume spike, fresh news catalyst, low float, trending on social media",
      "keyFactors": [
        "Gap: -52.1%",
        "Volume: 4.8x",
        "Float: 2.6M",
        "News: 12"
      ],
      "predictionDate": "2026-05-21",
      "targetDate": "2026-05-21",
      "checkDate": "2026-05-22",
      "priceType": "Pre-Market High (4:00-9:59 AM EST)",
      "gap_percent": -52.1,
      "volume_ratio": 4.8,
      "float": 2.6,
      "short_percent": 0.3,
      "news_count": 12
    },
    {
      "ticker": "LICN",
      "name": "Lichen International Limited",
      "predictedPrice": 1.09,
      "actualPrice": 1.11,
      "predictedMove": "+15% (Strong)",
      "actualMove": "+1.8%",
      "wasCorrect": false,
      "status": "PARTIAL",
      "confidence": 85,
      "reasoning": "4.7x volume spike, fresh news catalyst, low float, trending on social media",
      "keyFactors": [
        "Gap: -61.5%",
        "Volume: 4.7x",
        "Float: 16.3M",
        "News: 7"
      ],
      "predictionDate": "2026-05-21",
      "targetDate": "2026-05-21",
      "checkDate": "2026-05-22",
      "priceType": "Pre-Market High (4:00-9:59 AM EST)",
      "gap_percent": -61.5,
      "volume_ratio": 4.7,
      "float": 16.3,
      "short_percent": 0.0,
      "news_count": 7
    },
    {
      "ticker": "VIDA",
      "name": "VIDA Global Inc.",
      "predictedPrice": 4.15,
      "actualPrice": 5.79,
      "predictedMove": "+21% (Major Move)",
      "actualMove": "+39.5%",
      "wasCorrect": false,
      "status": "PARTIAL",
      "confidence": 71,
      "reasoning": "\u26a0\ufe0f EXTREME 61.5x volume (SUSPICIOUS), Strong 81.2% gap, fresh news catalyst, low float, trending on social media",
      "keyFactors": [
        "Gap: 81.2%",
        "Volume: 61.5x",
        "Float: 6.2M",
        "News: 1"
      ],
      "predictionDate": "2026-05-21",
      "targetDate": "2026-05-21",
      "checkDate": "2026-05-22",
      "priceType": "Pre-Market High (4:00-9:59 AM EST)",
      "gap_percent": 81.2,
      "volume_ratio": 61.5,
      "float": 6.2,
      "short_percent": 0.0,
      "news_count": 1
    },
    {
      "ticker": "ARTL",
      "name": "Artelo Biosciences, Inc.",
      "predictedPrice": 1.71,
      "actualPrice": 1.39,
      "predictedMove": "+20% (Strong)",
      "actualMove": "-18.7%",
      "wasCorrect": false,
      "status": "WRONG",
      "confidence": 95,
      "reasoning": "4.9x volume spike, Strong 43.7% gap, fresh news catalyst, low float, trending on social media",
      "keyFactors": [
        "Gap: 43.7%",
        "Volume: 4.9x",
        "Float: 2.1M",
        "Short: 7%",
        "News: 16"
      ],
      "predictionDate": "2026-05-27",
      "targetDate": "2026-05-27",
      "checkDate": "2026-05-28",
      "priceType": "Pre-Market High (4:00-9:59 AM EST)",
      "gap_percent": 43.7,
      "volume_ratio": 4.9,
      "float": 2.1,
      "short_percent": 6.7,
      "news_count": 16
    },
    {
      "ticker": "ECOR",
      "name": "electroCore, Inc.",
      "predictedPrice": 8.91,
      "actualPrice": 9.28,
      "predictedMove": "+19% (Strong)",
      "actualMove": "+4.2%",
      "wasCorrect": false,
      "status": "PARTIAL",
      "confidence": 95,
      "reasoning": "10.7x volume spike, Strong 33.6% gap, fresh news catalyst, low float, trending on social media",
      "keyFactors": [
        "Gap: 33.6%",
        "Volume: 10.7x",
        "Float: 5.3M",
        "News: 10"
      ],
      "predictionDate": "2026-05-27",
      "targetDate": "2026-05-27",
      "checkDate": "2026-05-28",
      "priceType": "Pre-Market High (4:00-9:59 AM EST)",
      "gap_percent": 33.6,
      "volume_ratio": 10.7,
      "float": 5.3,
      "short_percent": 4.4,
      "news_count": 10
    },
    {
      "ticker": "CMND",
      "name": "Clearmind Medicine Inc.",
      "predictedPrice": 2.59,
      "actualPrice": 2.66,
      "predictedMove": "+10% (Moderate)",
      "actualMove": "+2.7%",
      "wasCorrect": false,
      "status": "PARTIAL",
      "confidence": 95,
      "reasoning": "Strong 14.6% gap, fresh news catalyst, low float",
      "keyFactors": [
        "Gap: 14.6%",
        "Volume: 1.3x",
        "Float: 0.2M",
        "News: 11"
      ],
      "predictionDate": "2026-05-27",
      "targetDate": "2026-05-27",
      "checkDate": "2026-05-28",
      "priceType": "Pre-Market High (4:00-9:59 AM EST)",
      "gap_percent": 14.6,
      "volume_ratio": 1.3,
      "float": 0.2,
      "short_percent": 4.3,
      "news_count": 11
    },
    {
      "ticker": "CRBP",
      "name": "Corbus Pharmaceuticals Holdings, Inc.",
      "predictedPrice": 7.91,
      "actualPrice": 9.0,
      "predictedMove": "+12% (Strong)",
      "actualMove": "+13.8%",
      "wasCorrect": true,
      "status": "PERFECT",
      "confidence": 95,
      "reasoning": "8.0x volume spike, fresh news catalyst, low float, trending on social media",
      "keyFactors": [
        "Gap: -30.3%",
        "Volume: 8.0x",
        "Float: 12.7M",
        "Short: 9%",
        "News: 18"
      ],
      "predictionDate": "2026-05-27",
      "targetDate": "2026-05-27",
      "checkDate": "2026-05-28",
      "priceType": "Pre-Market High (4:00-9:59 AM EST)",
      "gap_percent": -30.3,
      "volume_ratio": 8.0,
      "float": 12.7,
      "short_percent": 9.2,
      "news_count": 18
    },
    {
      "ticker": "VGAS",
      "name": "Verde Clean Fuels, Inc.",
      "predictedPrice": 1.73,
      "actualPrice": 1.78,
      "predictedMove": "+8% (Moderate)",
      "actualMove": "+2.9%",
      "wasCorrect": false,
      "status": "PARTIAL",
      "confidence": 95,
      "reasoning": "3.5x volume spike, fresh news catalyst, low float, trending on social media",
      "keyFactors": [
        "Gap: -4.4%",
        "Volume: 3.5x",
        "Float: 1.0M",
        "News: 1"
      ],
      "predictionDate": "2026-05-27",
      "targetDate": "2026-05-27",
      "checkDate": "2026-05-28",
      "priceType": "Pre-Market High (4:00-9:59 AM EST)",
      "gap_percent": -4.4,
      "volume_ratio": 3.5,
      "float": 1.0,
      "short_percent": 3.1,
      "news_count": 1
    },
    {
      "ticker": "SEGG",
      "name": "Sports Entertainment Gaming Global Corporation",
      "predictedPrice": 1.4,
      "actualPrice": 1.75,
      "predictedMove": "+13% (Strong)",
      "actualMove": "+25.0%",
      "wasCorrect": false,
      "status": "PARTIAL",
      "confidence": 95,
      "reasoning": "fresh news catalyst, low float, high short interest (19%), trending on social media",
      "keyFactors": [
        "Gap: -26.7%",
        "Volume: 1.3x",
        "Float: 4.3M",
        "Short: 19%",
        "News: 6"
      ],
      "predictionDate": "2026-05-27",
      "targetDate": "2026-05-27",
      "checkDate": "2026-05-28",
      "priceType": "Pre-Market High (4:00-9:59 AM EST)",
      "gap_percent": -26.7,
      "volume_ratio": 1.3,
      "float": 4.3,
      "short_percent": 19.1,
      "news_count": 6
    },
    {
      "ticker": "UZX",
      "name": "Linkage Global Inc",
      "predictedPrice": 0.77,
      "actualPrice": 1.29,
      "predictedMove": "+28% (Major Move)",
      "actualMove": "+67.5%",
      "wasCorrect": false,
      "status": "PARTIAL",
      "confidence": 94,
      "reasoning": "\u26a0\ufe0f Very high 41.7x volume, Strong 72.7% gap, fresh news catalyst, low float, trending on social media",
      "keyFactors": [
        "Gap: 72.7%",
        "Volume: 41.7x",
        "Float: 1.9M",
        "News: 6"
      ],
      "predictionDate": "2026-05-27",
      "targetDate": "2026-05-27",
      "checkDate": "2026-05-28",
      "priceType": "Pre-Market High (4:00-9:59 AM EST)",
      "gap_percent": 72.7,
      "volume_ratio": 41.7,
      "float": 1.9,
      "short_percent": 0.0,
      "news_count": 6
    },
    {
      "ticker": "PLYX",
      "name": "Polaryx Therapeutics, Inc.",
      "predictedPrice": 2.58,
      "actualPrice": 2.75,
      "predictedMove": "+13% (Strong)",
      "actualMove": "+6.6%",
      "wasCorrect": false,
      "status": "PARTIAL",
      "confidence": 87,
      "reasoning": "elevated volume, fresh news catalyst, low float, trending on social media",
      "keyFactors": [
        "Gap: -28.3%",
        "Volume: 2.5x",
        "Float: 5.0M",
        "News: 4"
      ],
      "predictionDate": "2026-05-27",
      "targetDate": "2026-05-27",
      "checkDate": "2026-05-28",
      "priceType": "Pre-Market High (4:00-9:59 AM EST)",
      "gap_percent": -28.3,
      "volume_ratio": 2.5,
      "float": 5.0,
      "short_percent": 1.4,
      "news_count": 4
    },
    {
      "ticker": "PLUG",
      "name": "Plug Power Inc.",
      "predictedPrice": 3.84,
      "actualPrice": 3.93,
      "predictedMove": "+5% (Moderate)",
      "actualMove": "+2.3%",
      "wasCorrect": false,
      "status": "PARTIAL",
      "confidence": 85,
      "reasoning": "fresh news catalyst, high short interest (28%)",
      "keyFactors": [
        "Gap: 1.6%",
        "Volume: 1.5x",
        "Float: 1331.0M",
        "Short: 28%",
        "News: 11"
      ],
      "predictionDate": "2026-05-27",
      "targetDate": "2026-05-27",
      "checkDate": "2026-05-28",
      "priceType": "Pre-Market High (4:00-9:59 AM EST)",
      "gap_percent": 1.6,
      "volume_ratio": 1.5,
      "float": 1331.0,
      "short_percent": 27.8,
      "news_count": 11
    },
    {
      "ticker": "CSHR",
      "name": "CoinShares PLC",
      "predictedPrice": 4.91,
      "actualPrice": 5.0,
      "predictedMove": "+3%",
      "actualMove": "+1.8%",
      "wasCorrect": false,
      "status": "PARTIAL",
      "confidence": 80,
      "reasoning": "3.7x volume spike, fresh news catalyst, trending on social media",
      "keyFactors": [
        "Gap: -6.8%",
        "Volume: 3.7x",
        "Float: 131.8M",
        "News: 10"
      ],
      "predictionDate": "2026-05-27",
      "targetDate": "2026-05-27",
      "checkDate": "2026-05-28",
      "priceType": "Pre-Market High (4:00-9:59 AM EST)",
      "gap_percent": -6.8,
      "volume_ratio": 3.7,
      "float": 131.8,
      "short_percent": 0.7,
      "news_count": 10
    },
    {
      "ticker": "AIRJ",
      "name": "AirJoule Technologies Corporation",
      "predictedPrice": 4.87,
      "actualPrice": 5.15,
      "predictedMove": "+5% (Moderate)",
      "actualMove": "+5.7%",
      "wasCorrect": false,
      "status": "PARTIAL",
      "confidence": 95,
      "reasoning": "elevated volume, Strong 14.9% gap, fresh news catalyst, trending on social media",
      "keyFactors": [
        "Gap: 14.9%",
        "Volume: 2.2x",
        "Float: 31.1M",
        "Short: 6%",
        "News: 11"
      ],
      "predictionDate": "2026-05-28",
      "targetDate": "2026-05-28",
      "checkDate": "2026-05-29",
      "priceType": "Pre-Market High (4:00-9:59 AM EST)",
      "gap_percent": 14.9,
      "volume_ratio": 2.2,
      "float": 31.1,
      "short_percent": 6.5,
      "news_count": 11
    },
    {
      "ticker": "VTIX",
      "name": "Virtuix Holdings Inc.",
      "predictedPrice": 4.39,
      "actualPrice": 4.55,
      "predictedMove": "+23% (Major Move)",
      "actualMove": "+3.6%",
      "wasCorrect": false,
      "status": "PARTIAL",
      "confidence": 95,
      "reasoning": "\u26a0\ufe0f Very high 38.7x volume, Strong 46.3% gap, fresh news catalyst, low float, trending on social media",
      "keyFactors": [
        "Gap: 46.3%",
        "Volume: 38.7x",
        "Float: 11.5M",
        "Short: 14%",
        "News: 11"
      ],
      "predictionDate": "2026-05-28",
      "targetDate": "2026-05-28",
      "checkDate": "2026-05-29",
      "priceType": "Pre-Market High (4:00-9:59 AM EST)",
      "gap_percent": 46.3,
      "volume_ratio": 38.7,
      "float": 11.5,
      "short_percent": 14.4,
      "news_count": 11
    },
    {
      "ticker": "SNGX",
      "name": "Soligenix, Inc.",
      "predictedPrice": 0.87,
      "actualPrice": 0.88,
      "predictedMove": "+19% (Strong)",
      "actualMove": "+1.1%",
      "wasCorrect": false,
      "status": "PARTIAL",
      "confidence": 95,
      "reasoning": "10.0x volume spike, Strong 69.7% gap, fresh news catalyst, low float, trending on social media",
      "keyFactors": [
        "Gap: 69.7%",
        "Volume: 10.0x",
        "Float: 14.0M",
        "Short: 10%",
        "News: 15"
      ],
      "predictionDate": "2026-05-28",
      "targetDate": "2026-05-28",
      "checkDate": "2026-05-29",
      "priceType": "Pre-Market High (4:00-9:59 AM EST)",
      "gap_percent": 69.7,
      "volume_ratio": 10.0,
      "float": 14.0,
      "short_percent": 9.9,
      "news_count": 15
    },
    {
      "ticker": "HTCO",
      "name": "High-Trend International Group",
      "predictedPrice": 3.1,
      "actualPrice": 3.8,
      "predictedMove": "+22% (Major Move)",
      "actualMove": "+22.6%",
      "wasCorrect": false,
      "status": "PARTIAL",
      "confidence": 95,
      "reasoning": "9.4x volume spike, fresh news catalyst, low float, trending on social media",
      "keyFactors": [
        "Gap: -45.4%",
        "Volume: 9.4x",
        "Float: 3.2M",
        "Short: 10%",
        "News: 3"
      ],
      "predictionDate": "2026-05-28",
      "targetDate": "2026-05-28",
      "checkDate": "2026-05-29",
      "priceType": "Pre-Market High (4:00-9:59 AM EST)",
      "gap_percent": -45.4,
      "volume_ratio": 9.4,
      "float": 3.2,
      "short_percent": 9.8,
      "news_count": 3
    },
    {
      "ticker": "CIIT",
      "name": "Tianci International, Inc.",
      "predictedPrice": 1.25,
      "actualPrice": 1.27,
      "predictedMove": "+8% (Moderate)",
      "actualMove": "+1.7%",
      "wasCorrect": false,
      "status": "PARTIAL",
      "confidence": 95,
      "reasoning": "5.0x volume spike, fresh news catalyst, low float, trending on social media",
      "keyFactors": [
        "Gap: -4.4%",
        "Volume: 5.0x",
        "Float: 1.3M",
        "Short: 6%",
        "News: 1"
      ],
      "predictionDate": "2026-05-28",
      "targetDate": "2026-05-28",
      "checkDate": "2026-05-29",
      "priceType": "Pre-Market High (4:00-9:59 AM EST)",
      "gap_percent": -4.4,
      "volume_ratio": 5.0,
      "float": 1.3,
      "short_percent": 5.7,
      "news_count": 1
    },
    {
      "ticker": "DSX",
      "name": "Diana Shipping Inc.",
      "predictedPrice": 2.52,
      "actualPrice": 2.67,
      "predictedMove": "+4%",
      "actualMove": "+6.0%",
      "wasCorrect": false,
      "status": "PARTIAL",
      "confidence": 95,
      "reasoning": "5.0x volume spike, fresh news catalyst, trending on social media",
      "keyFactors": [
        "Gap: -7.4%",
        "Volume: 5.0x",
        "Float: 61.4M",
        "News: 12"
      ],
      "predictionDate": "2026-05-28",
      "targetDate": "2026-05-28",
      "checkDate": "2026-05-29",
      "priceType": "Pre-Market High (4:00-9:59 AM EST)",
      "gap_percent": -7.4,
      "volume_ratio": 5.0,
      "float": 61.4,
      "short_percent": 3.6,
      "news_count": 12
    },
    {
      "ticker": "LIQT",
      "name": "LiqTech International, Inc.",
      "predictedPrice": 1.25,
      "actualPrice": 1.26,
      "predictedMove": "+21% (Major Move)",
      "actualMove": "+0.8%",
      "wasCorrect": false,
      "status": "PARTIAL",
      "confidence": 87,
      "reasoning": "\u26a0\ufe0f Very high 38.7x volume, fresh news catalyst, low float, trending on social media",
      "keyFactors": [
        "Gap: -30.7%",
        "Volume: 38.7x",
        "Float: 7.7M",
        "News: 11"
      ],
      "predictionDate": "2026-05-28",
      "targetDate": "2026-05-28",
      "checkDate": "2026-05-29",
      "priceType": "Pre-Market High (4:00-9:59 AM EST)",
      "gap_percent": -30.7,
      "volume_ratio": 38.7,
      "float": 7.7,
      "short_percent": 1.2,
      "news_count": 11
    },
    {
      "ticker": "NSPR",
      "name": "InspireMD, Inc.",
      "predictedPrice": 0.88,
      "actualPrice": 0.93,
      "predictedMove": "+3%",
      "actualMove": "+5.5%",
      "wasCorrect": false,
      "status": "PARTIAL",
      "confidence": 80,
      "reasoning": "elevated volume, fresh news catalyst",
      "keyFactors": [
        "Gap: -7.4%",
        "Volume: 2.1x",
        "Float: 26.5M",
        "News: 10"
      ],
      "predictionDate": "2026-05-28",
      "targetDate": "2026-05-28",
      "checkDate": "2026-05-29",
      "priceType": "Pre-Market High (4:00-9:59 AM EST)",
      "gap_percent": -7.4,
      "volume_ratio": 2.1,
      "float": 26.5,
      "short_percent": 0.1,
      "news_count": 10
    },
    {
      "ticker": "NIO",
      "name": "NIO Inc.",
      "predictedPrice": 5.75,
      "actualPrice": 5.77,
      "predictedMove": "+3%",
      "actualMove": "+0.3%",
      "wasCorrect": false,
      "status": "PARTIAL",
      "confidence": 80,
      "reasoning": "Solid 9.3% gap, fresh news catalyst",
      "keyFactors": [
        "Gap: 9.3%",
        "Volume: 1.3x",
        "Float: 1888.4M",
        "Short: 7%",
        "News: 11"
      ],
      "predictionDate": "2026-05-28",
      "targetDate": "2026-05-28",
      "checkDate": "2026-05-29",
      "priceType": "Pre-Market High (4:00-9:59 AM EST)",
      "gap_percent": 9.3,
      "volume_ratio": 1.3,
      "float": 1888.4,
      "short_percent": 7.0,
      "news_count": 11
    },
    {
      "ticker": "CHR",
      "name": "Cheer Holding, Inc.",
      "predictedPrice": 2.59,
      "actualPrice": 2.95,
      "predictedMove": "+13% (Strong)",
      "actualMove": "+13.9%",
      "wasCorrect": true,
      "status": "PERFECT",
      "confidence": 95,
      "reasoning": "Strong 25.1% gap, fresh news catalyst, low float, trending on social media",
      "keyFactors": [
        "Gap: 25.1%",
        "Volume: 1.7x",
        "Float: 1.3M",
        "Short: 5%",
        "News: 6"
      ],
      "predictionDate": "2026-06-02",
      "targetDate": "2026-06-02",
      "checkDate": "2026-06-03",
      "priceType": "Pre-Market High (4:00-9:59 AM EST)",
      "gap_percent": 25.1,
      "volume_ratio": 1.7,
      "float": 1.3,
      "short_percent": 5.3,
      "news_count": 6
    },
    {
      "ticker": "DBGI",
      "name": "Digital Brands Group, Inc.",
      "predictedPrice": 0.84,
      "actualPrice": 1.22,
      "predictedMove": "+20% (Strong)",
      "actualMove": "+45.2%",
      "wasCorrect": false,
      "status": "PARTIAL",
      "confidence": 95,
      "reasoning": "11.2x volume spike, Strong 73.3% gap, fresh news catalyst, trending on social media",
      "keyFactors": [
        "Gap: 73.3%",
        "Volume: 11.2x",
        "Float: 23.0M",
        "Short: 5%",
        "News: 2"
      ],
      "predictionDate": "2026-06-02",
      "targetDate": "2026-06-02",
      "checkDate": "2026-06-03",
      "priceType": "Pre-Market High (4:00-9:59 AM EST)",
      "gap_percent": 73.3,
      "volume_ratio": 11.2,
      "float": 23.0,
      "short_percent": 5.5,
      "news_count": 2
    },
    {
      "ticker": "GNTA",
      "name": "Genenta Science S.p.A.",
      "predictedPrice": 1.65,
      "actualPrice": 2.0,
      "predictedMove": "+24% (Major Move)",
      "actualMove": "+21.2%",
      "wasCorrect": false,
      "status": "PARTIAL",
      "confidence": 95,
      "reasoning": "25.3x volume spike, Strong 60.2% gap, fresh news catalyst, low float, trending on social media",
      "keyFactors": [
        "Gap: 60.2%",
        "Volume: 25.3x",
        "Float: 13.9M",
        "News: 15"
      ],
      "predictionDate": "2026-06-02",
      "targetDate": "2026-06-02",
      "checkDate": "2026-06-03",
      "priceType": "Pre-Market High (4:00-9:59 AM EST)",
      "gap_percent": 60.2,
      "volume_ratio": 25.3,
      "float": 13.9,
      "short_percent": 0.0,
      "news_count": 15
    },
    {
      "ticker": "CRMT",
      "name": "America's Car-Mart, Inc.",
      "predictedPrice": 6.86,
      "actualPrice": 7.2,
      "predictedMove": "+30% (Major Move)",
      "actualMove": "+5.0%",
      "wasCorrect": false,
      "status": "PARTIAL",
      "confidence": 95,
      "reasoning": "16.2x volume spike, fresh news catalyst, low float, high short interest (25%), trending on social media",
      "keyFactors": [
        "Gap: -44.2%",
        "Volume: 16.2x",
        "Float: 4.2M",
        "Short: 25%",
        "News: 13"
      ],
      "predictionDate": "2026-06-02",
      "targetDate": "2026-06-02",
      "checkDate": "2026-06-03",
      "priceType": "Pre-Market High (4:00-9:59 AM EST)",
      "gap_percent": -44.2,
      "volume_ratio": 16.2,
      "float": 4.2,
      "short_percent": 24.8,
      "news_count": 13
    },
    {
      "ticker": "SPCE",
      "name": "Virgin Galactic Holdings, Inc.",
      "predictedPrice": 7.52,
      "actualPrice": 7.25,
      "predictedMove": "+13% (Strong)",
      "actualMove": "-3.6%",
      "wasCorrect": false,
      "status": "WRONG",
      "confidence": 95,
      "reasoning": "3.8x volume spike, Strong 21.7% gap, fresh news catalyst, high short interest (23%), trending on social media",
      "keyFactors": [
        "Gap: 21.7%",
        "Volume: 3.8x",
        "Float: 100.5M",
        "Short: 23%",
        "News: 20"
      ],
      "predictionDate": "2026-06-02",
      "targetDate": "2026-06-02",
      "checkDate": "2026-06-03",
      "priceType": "Pre-Market High (4:00-9:59 AM EST)",
      "gap_percent": 21.7,
      "volume_ratio": 3.8,
      "float": 100.5,
      "short_percent": 22.6,
      "news_count": 20
    },
    {
      "ticker": "OPTU",
      "name": "OPTU",
      "predictedPrice": 1.16,
      "actualPrice": 1.24,
      "predictedMove": "+28% (Major Move)",
      "actualMove": "+6.9%",
      "wasCorrect": false,
      "status": "PARTIAL",
      "confidence": 95,
      "reasoning": "27.8x volume spike, Strong 76.3% gap, fresh news catalyst, high short interest (33%), trending on social media",
      "keyFactors": [
        "Gap: 76.3%",
        "Volume: 27.8x",
        "Float: 252.5M",
        "Short: 33%",
        "News: 16"
      ],
      "predictionDate": "2026-06-02",
      "targetDate": "2026-06-02",
      "checkDate": "2026-06-03",
      "priceType": "Pre-Market High (4:00-9:59 AM EST)",
      "gap_percent": 76.3,
      "volume_ratio": 27.8,
      "float": 252.5,
      "short_percent": 33.2,
      "news_count": 16
    },
    {
      "ticker": "AMC",
      "name": "AMC Entertainment Holdings, Inc.",
      "predictedPrice": 2.12,
      "actualPrice": 2.18,
      "predictedMove": "+8% (Moderate)",
      "actualMove": "+2.8%",
      "wasCorrect": false,
      "status": "PARTIAL",
      "confidence": 95,
      "reasoning": "4.2x volume spike, Strong 22.5% gap, fresh news catalyst, trending on social media",
      "keyFactors": [
        "Gap: 22.5%",
        "Volume: 4.2x",
        "Float: 562.6M",
        "Short: 8%",
        "News: 11"
      ],
      "predictionDate": "2026-06-02",
      "targetDate": "2026-06-02",
      "checkDate": "2026-06-03",
      "priceType": "Pre-Market High (4:00-9:59 AM EST)",
      "gap_percent": 22.5,
      "volume_ratio": 4.2,
      "float": 562.6,
      "short_percent": 8.5,
      "news_count": 11
    },
    {
      "ticker": "SUUN",
      "name": "PowerBank Corporation",
      "predictedPrice": 1.53,
      "actualPrice": 1.57,
      "predictedMove": "+16% (Strong)",
      "actualMove": "+2.6%",
      "wasCorrect": false,
      "status": "PARTIAL",
      "confidence": 95,
      "reasoning": "3.4x volume spike, Strong 76.9% gap, fresh news catalyst, trending on social media",
      "keyFactors": [
        "Gap: 76.9%",
        "Volume: 3.4x",
        "Float: 45.1M",
        "News: 14"
      ],
      "predictionDate": "2026-06-02",
      "targetDate": "2026-06-02",
      "checkDate": "2026-06-03",
      "priceType": "Pre-Market High (4:00-9:59 AM EST)",
      "gap_percent": 76.9,
      "volume_ratio": 3.4,
      "float": 45.1,
      "short_percent": 1.7,
      "news_count": 14
    },
    {
      "ticker": "NXTC",
      "name": "NextCure, Inc.",
      "predictedPrice": 3.38,
      "actualPrice": 3.66,
      "predictedMove": "+25% (Major Move)",
      "actualMove": "+8.3%",
      "wasCorrect": false,
      "status": "PARTIAL",
      "confidence": 95,
      "reasoning": "15.7x volume spike, fresh news catalyst, low float, trending on social media",
      "keyFactors": [
        "Gap: -45.5%",
        "Volume: 15.7x",
        "Float: 2.3M",
        "News: 5"
      ],
      "predictionDate": "2026-06-02",
      "targetDate": "2026-06-02",
      "checkDate": "2026-06-03",
      "priceType": "Pre-Market High (4:00-9:59 AM EST)",
      "gap_percent": -45.5,
      "volume_ratio": 15.7,
      "float": 2.3,
      "short_percent": 1.6,
      "news_count": 5
    },
    {
      "ticker": "JSPR",
      "name": "Jasper Therapeutics, Inc.",
      "predictedPrice": 0.53,
      "actualPrice": 0.61,
      "predictedMove": "+15% (Strong)",
      "actualMove": "+15.1%",
      "wasCorrect": true,
      "status": "PERFECT",
      "confidence": 95,
      "reasoning": "10.5x volume spike, fresh news catalyst, trending on social media",
      "keyFactors": [
        "Gap: -35.6%",
        "Volume: 10.5x",
        "Float: 21.9M",
        "Short: 9%",
        "News: 6"
      ],
      "predictionDate": "2026-06-02",
      "targetDate": "2026-06-02",
      "checkDate": "2026-06-03",
      "priceType": "Pre-Market High (4:00-9:59 AM EST)",
      "gap_percent": -35.6,
      "volume_ratio": 10.5,
      "float": 21.9,
      "short_percent": 9.0,
      "news_count": 6
    },
    {
      "ticker": "JZ",
      "name": "Jianzhi Education Technology Group Company Limited",
      "predictedPrice": 0.7,
      "actualPrice": 0.58,
      "predictedMove": "+14% (Strong)",
      "actualMove": "-17.3%",
      "wasCorrect": false,
      "status": "WRONG",
      "confidence": 80,
      "reasoning": "5.4x volume spike, fresh news catalyst, trending on social media",
      "keyFactors": [
        "Gap: -77.4%",
        "Volume: 5.4x",
        "Float: 467.0M",
        "News: 11"
      ],
      "predictionDate": "2026-06-03",
      "targetDate": "2026-06-03",
      "checkDate": "2026-06-04",
      "priceType": "Pre-Market High (4:00-9:59 AM EST)",
      "gap_percent": -77.4,
      "volume_ratio": 5.4,
      "float": 467.0,
      "short_percent": 0.1,
      "news_count": 11
    },
    {
      "ticker": "ACXP",
      "name": "Acurx Pharmaceuticals, Inc.",
      "predictedPrice": 1.8,
      "actualPrice": 1.93,
      "predictedMove": "+6% (Moderate)",
      "actualMove": "+7.2%",
      "wasCorrect": false,
      "status": "PARTIAL",
      "confidence": 80,
      "reasoning": "fresh news catalyst, low float",
      "keyFactors": [
        "Gap: -6.7%",
        "Volume: 1.7x",
        "Float: 4.1M",
        "News: 10"
      ],
      "predictionDate": "2026-06-03",
      "targetDate": "2026-06-03",
      "checkDate": "2026-06-04",
      "priceType": "Pre-Market High (4:00-9:59 AM EST)",
      "gap_percent": -6.7,
      "volume_ratio": 1.7,
      "float": 4.1,
      "short_percent": 3.4,
      "news_count": 10
    },
    {
      "ticker": "FULC",
      "name": "Fulcrum Therapeutics, Inc.",
      "predictedPrice": 3.14,
      "actualPrice": 3.25,
      "predictedMove": "+19% (Strong)",
      "actualMove": "+3.5%",
      "wasCorrect": false,
      "status": "PARTIAL",
      "confidence": 77,
      "reasoning": "\u26a0\ufe0f Very high 31.6x volume, fresh news catalyst, trending on social media",
      "keyFactors": [
        "Gap: -51.1%",
        "Volume: 31.6x",
        "Float: 48.0M",
        "Short: 12%",
        "News: 20"
      ],
      "predictionDate": "2026-06-03",
      "targetDate": "2026-06-03",
      "checkDate": "2026-06-04",
      "priceType": "Pre-Market High (4:00-9:59 AM EST)",
      "gap_percent": -51.1,
      "volume_ratio": 31.6,
      "float": 48.0,
      "short_percent": 11.8,
      "news_count": 20
    },
    {
      "ticker": "BITO",
      "name": "ProShares Bitcoin ETF",
      "predictedPrice": 9.17,
      "actualPrice": 9.18,
      "predictedMove": "+2%",
      "actualMove": "+0.1%",
      "wasCorrect": false,
      "status": "PARTIAL",
      "confidence": 58,
      "reasoning": "fresh news catalyst",
      "keyFactors": [
        "Gap: -5.9%",
        "Volume: 1.8x",
        "Float: 1000.0M",
        "News: 10"
      ],
      "predictionDate": "2026-06-03",
      "targetDate": "2026-06-03",
      "checkDate": "2026-06-04",
      "priceType": "Pre-Market High (4:00-9:59 AM EST)",
      "gap_percent": -5.9,
      "volume_ratio": 1.8,
      "float": 1000.0,
      "short_percent": 0.0,
      "news_count": 10
    },
    {
      "ticker": "BBXIA",
      "name": "BBX Capital, Inc.",
      "predictedPrice": 3.84,
      "actualPrice": 3.84,
      "predictedMove": "+16% (Strong)",
      "actualMove": "-0.0%",
      "wasCorrect": false,
      "status": "WRONG",
      "confidence": 95,
      "reasoning": "6.6x volume spike, Strong 27.2% gap, low float, trending on social media",
      "keyFactors": [
        "Gap: 27.2%",
        "Volume: 6.6x",
        "Float: 5.0M"
      ],
      "predictionDate": "2026-06-04",
      "targetDate": "2026-06-04",
      "checkDate": "2026-06-05",
      "priceType": "Pre-Market High (4:00-9:59 AM EST)",
      "gap_percent": 27.2,
      "volume_ratio": 6.6,
      "float": 5.0,
      "short_percent": 0.0,
      "news_count": 0
    },
    {
      "ticker": "LSF",
      "name": "Laird Superfood, Inc.",
      "predictedPrice": 3.19,
      "actualPrice": 3.29,
      "predictedMove": "+5% (Moderate)",
      "actualMove": "+3.1%",
      "wasCorrect": false,
      "status": "PARTIAL",
      "confidence": 75,
      "reasoning": "fresh news catalyst, low float",
      "keyFactors": [
        "Gap: -5.1%",
        "Volume: 1.3x",
        "Float: 8.3M",
        "News: 10"
      ],
      "predictionDate": "2026-06-04",
      "targetDate": "2026-06-04",
      "checkDate": "2026-06-05",
      "priceType": "Pre-Market High (4:00-9:59 AM EST)",
      "gap_percent": -5.1,
      "volume_ratio": 1.3,
      "float": 8.3,
      "short_percent": 1.1,
      "news_count": 10
    },
    {
      "ticker": "SEED",
      "name": "Origin Agritech Limited",
      "predictedPrice": 1.09,
      "actualPrice": 1.09,
      "predictedMove": "+5%",
      "actualMove": "+0.1%",
      "wasCorrect": false,
      "status": "PARTIAL",
      "confidence": 71,
      "reasoning": "fresh news catalyst, low float",
      "keyFactors": [
        "Gap: -3.5%",
        "Volume: 1.5x",
        "Float: 6.9M",
        "News: 4"
      ],
      "predictionDate": "2026-06-04",
      "targetDate": "2026-06-04",
      "checkDate": "2026-06-05",
      "priceType": "Pre-Market High (4:00-9:59 AM EST)",
      "gap_percent": -3.5,
      "volume_ratio": 1.5,
      "float": 6.9,
      "short_percent": 0.5,
      "news_count": 4
    },
    {
      "ticker": "IPDN",
      "name": "Professional Diversity Network, Inc.",
      "predictedPrice": 0.68,
      "actualPrice": 0.68,
      "predictedMove": "+4%",
      "actualMove": "-0.5%",
      "wasCorrect": false,
      "status": "WRONG",
      "confidence": 66,
      "reasoning": "fresh news catalyst, low float",
      "keyFactors": [
        "Gap: -3.3%",
        "Volume: 1.3x",
        "Float: 8.5M",
        "News: 1"
      ],
      "predictionDate": "2026-06-04",
      "targetDate": "2026-06-04",
      "checkDate": "2026-06-05",
      "priceType": "Pre-Market High (4:00-9:59 AM EST)",
      "gap_percent": -3.3,
      "volume_ratio": 1.3,
      "float": 8.5,
      "short_percent": 1.5,
      "news_count": 1
    },
    {
      "ticker": "OCG",
      "name": "Oriental Culture Holding LTD",
      "predictedPrice": 1.8,
      "actualPrice": 2.79,
      "predictedMove": "+16% (Strong)",
      "actualMove": "+55.0%",
      "wasCorrect": false,
      "status": "PARTIAL",
      "confidence": 95,
      "reasoning": "26.5x volume spike, Solid 5.9% gap, fresh news catalyst, low float, trending on social media",
      "keyFactors": [
        "Gap: 5.9%",
        "Volume: 26.5x",
        "Float: 0.0M",
        "Short: 9%",
        "News: 7"
      ],
      "predictionDate": "2026-06-09",
      "targetDate": "2026-06-09",
      "checkDate": "2026-06-10",
      "priceType": "Pre-Market High (4:00-9:59 AM EST)",
      "gap_percent": 5.9,
      "volume_ratio": 26.5,
      "float": 0.0,
      "short_percent": 9.1,
      "news_count": 7
    },
    {
      "ticker": "LESL",
      "name": "Leslie's, Inc.",
      "predictedPrice": 8.18,
      "actualPrice": 8.67,
      "predictedMove": "+21% (Major Move)",
      "actualMove": "+6.0%",
      "wasCorrect": false,
      "status": "PARTIAL",
      "confidence": 95,
      "reasoning": "4.5x volume spike, Strong 59.5% gap, fresh news catalyst, low float, high short interest (17%), trending on social media",
      "keyFactors": [
        "Gap: 59.5%",
        "Volume: 4.5x",
        "Float: 9.1M",
        "Short: 17%",
        "News: 13"
      ],
      "predictionDate": "2026-06-10",
      "targetDate": "2026-06-10",
      "checkDate": "2026-06-11",
      "priceType": "Pre-Market High (4:00-9:59 AM EST)",
      "gap_percent": 59.5,
      "volume_ratio": 4.5,
      "float": 9.1,
      "short_percent": 16.9,
      "news_count": 13
    },
    {
      "ticker": "PAVS",
      "name": "Paranovus Entertainment Technology Ltd.",
      "predictedPrice": 1.02,
      "actualPrice": 1.65,
      "predictedMove": "+17% (Strong)",
      "actualMove": "+61.8%",
      "wasCorrect": false,
      "status": "PARTIAL",
      "confidence": 95,
      "reasoning": "\u26a0\ufe0f Very high 43.5x volume, Solid 8.4% gap, fresh news catalyst, low float, trending on social media",
      "keyFactors": [
        "Gap: 8.4%",
        "Volume: 43.5x",
        "Float: 0.3M",
        "News: 9"
      ],
      "predictionDate": "2026-06-10",
      "targetDate": "2026-06-10",
      "checkDate": "2026-06-11",
      "priceType": "Pre-Market High (4:00-9:59 AM EST)",
      "gap_percent": 8.4,
      "volume_ratio": 43.5,
      "float": 0.3,
      "short_percent": 1.9,
      "news_count": 9
    },
    {
      "ticker": "PCSA",
      "name": "Processa Pharmaceuticals, Inc.",
      "predictedPrice": 2.04,
      "actualPrice": 2.62,
      "predictedMove": "+11% (Strong)",
      "actualMove": "+28.5%",
      "wasCorrect": false,
      "status": "PARTIAL",
      "confidence": 95,
      "reasoning": "3.8x volume spike, fresh news catalyst, low float, trending on social media",
      "keyFactors": [
        "Gap: -15.9%",
        "Volume: 3.8x",
        "Float: 2.5M",
        "News: 5"
      ],
      "predictionDate": "2026-06-10",
      "targetDate": "2026-06-10",
      "checkDate": "2026-06-11",
      "priceType": "Pre-Market High (4:00-9:59 AM EST)",
      "gap_percent": -15.9,
      "volume_ratio": 3.8,
      "float": 2.5,
      "short_percent": 3.8,
      "news_count": 5
    },
    {
      "ticker": "RGNT",
      "name": "Regentis Biomaterials Ltd.",
      "predictedPrice": 2.41,
      "actualPrice": 2.5,
      "predictedMove": "+28% (Major Move)",
      "actualMove": "+3.7%",
      "wasCorrect": false,
      "status": "PARTIAL",
      "confidence": 92,
      "reasoning": "\u26a0\ufe0f Very high 34.5x volume, Strong 88.3% gap, fresh news catalyst, low float, trending on social media",
      "keyFactors": [
        "Gap: 88.3%",
        "Volume: 34.5x",
        "Float: 2.8M",
        "News: 11"
      ],
      "predictionDate": "2026-06-10",
      "targetDate": "2026-06-10",
      "checkDate": "2026-06-11",
      "priceType": "Pre-Market High (4:00-9:59 AM EST)",
      "gap_percent": 88.3,
      "volume_ratio": 34.5,
      "float": 2.8,
      "short_percent": 0.8,
      "news_count": 11
    },
    {
      "ticker": "EPSM",
      "name": "Epsium Enterprise Limited",
      "predictedPrice": 2.05,
      "actualPrice": 1.75,
      "predictedMove": "+28% (Major Move)",
      "actualMove": "-14.6%",
      "wasCorrect": false,
      "status": "WRONG",
      "confidence": 92,
      "reasoning": "\u26a0\ufe0f Very high 30.5x volume, Strong 72.3% gap, fresh news catalyst, low float, trending on social media",
      "keyFactors": [
        "Gap: 72.3%",
        "Volume: 30.5x",
        "Float: 2.1M",
        "News: 10"
      ],
      "predictionDate": "2026-06-10",
      "targetDate": "2026-06-10",
      "checkDate": "2026-06-11",
      "priceType": "Pre-Market High (4:00-9:59 AM EST)",
      "gap_percent": 72.3,
      "volume_ratio": 30.5,
      "float": 2.1,
      "short_percent": 0.1,
      "news_count": 10
    },
    {
      "ticker": "SLGB",
      "name": "Smart Logistics Global Limited",
      "predictedPrice": 0.73,
      "actualPrice": 1.13,
      "predictedMove": "+25% (Major Move)",
      "actualMove": "+54.8%",
      "wasCorrect": false,
      "status": "PARTIAL",
      "confidence": 92,
      "reasoning": "\u26a0\ufe0f EXTREME 62.9x volume (SUSPICIOUS), Strong 41.8% gap, fresh news catalyst, low float, trending on social media",
      "keyFactors": [
        "Gap: 41.8%",
        "Volume: 62.9x",
        "Float: 3.0M",
        "News: 10"
      ],
      "predictionDate": "2026-06-10",
      "targetDate": "2026-06-10",
      "checkDate": "2026-06-11",
      "priceType": "Pre-Market High (4:00-9:59 AM EST)",
      "gap_percent": 41.8,
      "volume_ratio": 62.9,
      "float": 3.0,
      "short_percent": 0.4,
      "news_count": 10
    },
    {
      "ticker": "ELPW",
      "name": "Elong Power Holding Limited",
      "predictedPrice": 1.16,
      "actualPrice": 1.34,
      "predictedMove": "+26% (Major Move)",
      "actualMove": "+15.5%",
      "wasCorrect": true,
      "status": "PERFECT",
      "confidence": 88,
      "reasoning": "\u26a0\ufe0f EXTREME 65.2x volume (SUSPICIOUS), Strong 50.5% gap, fresh news catalyst, low float, trending on social media",
      "keyFactors": [
        "Gap: 50.5%",
        "Volume: 65.2x",
        "Float: 1.2M",
        "Short: 10%",
        "News: 9"
      ],
      "predictionDate": "2026-06-10",
      "targetDate": "2026-06-10",
      "checkDate": "2026-06-11",
      "priceType": "Pre-Market High (4:00-9:59 AM EST)",
      "gap_percent": 50.5,
      "volume_ratio": 65.2,
      "float": 1.2,
      "short_percent": 10.0,
      "news_count": 9
    },
    {
      "ticker": "SPDN",
      "name": "Direxion Daily S&P 500 Bear 1X Shares",
      "predictedPrice": 8.86,
      "actualPrice": 8.96,
      "predictedMove": "+1%",
      "actualMove": "+1.1%",
      "wasCorrect": false,
      "status": "PARTIAL",
      "confidence": 69,
      "reasoning": "3.3x volume spike, fresh news catalyst",
      "keyFactors": [
        "Gap: 0.3%",
        "Volume: 3.3x",
        "Float: 1000.0M",
        "News: 5"
      ],
      "predictionDate": "2026-06-10",
      "targetDate": "2026-06-10",
      "checkDate": "2026-06-11",
      "priceType": "Pre-Market High (4:00-9:59 AM EST)",
      "gap_percent": 0.3,
      "volume_ratio": 3.3,
      "float": 1000.0,
      "short_percent": 0.0,
      "news_count": 5
    },
    {
      "ticker": "IZM",
      "name": "ICZOOM Group Inc.",
      "predictedPrice": 0.78,
      "actualPrice": 0.61,
      "predictedMove": "+26% (Major Move)",
      "actualMove": "-21.2%",
      "wasCorrect": false,
      "status": "WRONG",
      "confidence": 95,
      "reasoning": "15.6x volume spike, Strong 90.2% gap, fresh news catalyst, low float, trending on social media",
      "keyFactors": [
        "Gap: 90.2%",
        "Volume: 15.6x",
        "Float: 7.8M",
        "News: 3"
      ],
      "predictionDate": "2026-06-11",
      "targetDate": "2026-06-11",
      "checkDate": "2026-06-12",
      "priceType": "Pre-Market High (4:00-9:59 AM EST)",
      "gap_percent": 90.2,
      "volume_ratio": 15.6,
      "float": 7.8,
      "short_percent": 0.6,
      "news_count": 3
    },
    {
      "ticker": "HXHX",
      "name": "Haoxin Holdings Limited",
      "predictedPrice": 0.88,
      "actualPrice": 0.78,
      "predictedMove": "+20% (Major Move)",
      "actualMove": "-11.6%",
      "wasCorrect": false,
      "status": "WRONG",
      "confidence": 95,
      "reasoning": "elevated volume, Strong 73.2% gap, fresh news catalyst, low float, trending on social media",
      "keyFactors": [
        "Gap: 73.2%",
        "Volume: 2.7x",
        "Float: 2.5M",
        "News: 10"
      ],
      "predictionDate": "2026-06-11",
      "targetDate": "2026-06-11",
      "checkDate": "2026-06-12",
      "priceType": "Pre-Market High (4:00-9:59 AM EST)",
      "gap_percent": 73.2,
      "volume_ratio": 2.7,
      "float": 2.5,
      "short_percent": 1.3,
      "news_count": 10
    },
    {
      "ticker": "BATL",
      "name": "Battalion Oil Corporation",
      "predictedPrice": 2.06,
      "actualPrice": 2.22,
      "predictedMove": "+24% (Major Move)",
      "actualMove": "+7.8%",
      "wasCorrect": false,
      "status": "PARTIAL",
      "confidence": 95,
      "reasoning": "11.0x volume spike, Strong 57.3% gap, fresh news catalyst, low float, high short interest (95%), trending on social media",
      "keyFactors": [
        "Gap: 57.3%",
        "Volume: 11.0x",
        "Float: 13.3M",
        "Short: 95%",
        "News: 11"
      ],
      "predictionDate": "2026-06-11",
      "targetDate": "2026-06-11",
      "checkDate": "2026-06-12",
      "priceType": "Pre-Market High (4:00-9:59 AM EST)",
      "gap_percent": 57.3,
      "volume_ratio": 11.0,
      "float": 13.3,
      "short_percent": 94.9,
      "news_count": 11
    },
    {
      "ticker": "GLE",
      "name": "Global Engine Group Holding Limited",
      "predictedPrice": 0.67,
      "actualPrice": 0.68,
      "predictedMove": "+20% (Major Move)",
      "actualMove": "+1.9%",
      "wasCorrect": false,
      "status": "PARTIAL",
      "confidence": 95,
      "reasoning": "elevated volume, Strong 51.5% gap, fresh news catalyst, low float, trending on social media",
      "keyFactors": [
        "Gap: 51.5%",
        "Volume: 2.9x",
        "Float: 4.3M",
        "News: 16"
      ],
      "predictionDate": "2026-06-11",
      "targetDate": "2026-06-11",
      "checkDate": "2026-06-12",
      "priceType": "Pre-Market High (4:00-9:59 AM EST)",
      "gap_percent": 51.5,
      "volume_ratio": 2.9,
      "float": 4.3,
      "short_percent": 1.6,
      "news_count": 16
    },
    {
      "ticker": "AERT",
      "name": "Aeries Technology, Inc",
      "predictedPrice": 0.5,
      "actualPrice": 0.64,
      "predictedMove": "+13% (Strong)",
      "actualMove": "+28.6%",
      "wasCorrect": false,
      "status": "PARTIAL",
      "confidence": 95,
      "reasoning": "5.9x volume spike, fresh news catalyst, low float, trending on social media",
      "keyFactors": [
        "Gap: -36.6%",
        "Volume: 5.9x",
        "Float: 11.8M",
        "News: 8"
      ],
      "predictionDate": "2026-06-11",
      "targetDate": "2026-06-11",
      "checkDate": "2026-06-12",
      "priceType": "Pre-Market High (4:00-9:59 AM EST)",
      "gap_percent": -36.6,
      "volume_ratio": 5.9,
      "float": 11.8,
      "short_percent": 0.6,
      "news_count": 8
    },
    {
      "ticker": "CRMT",
      "name": "America's Car-Mart, Inc.",
      "predictedPrice": 2.37,
      "actualPrice": 2.67,
      "predictedMove": "+33% (Major Move)",
      "actualMove": "+12.7%",
      "wasCorrect": true,
      "status": "PERFECT",
      "confidence": 93,
      "reasoning": "\u26a0\ufe0f Very high 37.0x volume, fresh news catalyst, low float, high short interest (24%), trending on social media",
      "keyFactors": [
        "Gap: -55.0%",
        "Volume: 37.0x",
        "Float: 4.2M",
        "Short: 24%",
        "News: 14"
      ],
      "predictionDate": "2026-06-11",
      "targetDate": "2026-06-11",
      "checkDate": "2026-06-12",
      "priceType": "Pre-Market High (4:00-9:59 AM EST)",
      "gap_percent": -55.0,
      "volume_ratio": 37.0,
      "float": 4.2,
      "short_percent": 24.1,
      "news_count": 14
    },
    {
      "ticker": "OCUL",
      "name": "Ocular Therapeutix, Inc.",
      "predictedPrice": 8.74,
      "actualPrice": 9.6,
      "predictedMove": "+1%",
      "actualMove": "+9.8%",
      "wasCorrect": false,
      "status": "PARTIAL",
      "confidence": 79,
      "reasoning": "fresh news catalyst",
      "keyFactors": [
        "Gap: 3.2%",
        "Volume: 1.5x",
        "Float: 184.4M",
        "Short: 14%",
        "News: 10"
      ],
      "predictionDate": "2026-06-11",
      "targetDate": "2026-06-11",
      "checkDate": "2026-06-12",
      "priceType": "Pre-Market High (4:00-9:59 AM EST)",
      "gap_percent": 3.2,
      "volume_ratio": 1.5,
      "float": 184.4,
      "short_percent": 13.5,
      "news_count": 10
    },
    {
      "ticker": "SOXS",
      "name": "Direxion Daily Semiconductor Bear 3X Shares",
      "predictedPrice": 6.57,
      "actualPrice": 6.4,
      "predictedMove": "+3%",
      "actualMove": "-2.6%",
      "wasCorrect": false,
      "status": "WRONG",
      "confidence": 76,
      "reasoning": "Strong 10.8% gap, fresh news catalyst",
      "keyFactors": [
        "Gap: 10.8%",
        "Volume: 1.2x",
        "Float: 1000.0M",
        "News: 8"
      ],
      "predictionDate": "2026-06-11",
      "targetDate": "2026-06-11",
      "checkDate": "2026-06-12",
      "priceType": "Pre-Market High (4:00-9:59 AM EST)",
      "gap_percent": 10.8,
      "volume_ratio": 1.2,
      "float": 1000.0,
      "short_percent": 0.0,
      "news_count": 8
    },
    {
      "ticker": "SMCX",
      "name": "Defiance Daily Target 2X Long SMCI ETF",
      "predictedPrice": 9.66,
      "actualPrice": 11.95,
      "predictedMove": "+12% (Strong)",
      "actualMove": "+23.7%",
      "wasCorrect": false,
      "status": "PARTIAL",
      "confidence": 66,
      "reasoning": "5.6x volume spike, fresh news catalyst, trending on social media",
      "keyFactors": [
        "Gap: -55.7%",
        "Volume: 5.6x",
        "Float: 1000.0M",
        "News: 2"
      ],
      "predictionDate": "2026-06-11",
      "targetDate": "2026-06-11",
      "checkDate": "2026-06-12",
      "priceType": "Pre-Market High (4:00-9:59 AM EST)",
      "gap_percent": -55.7,
      "volume_ratio": 5.6,
      "float": 1000.0,
      "short_percent": 0.0,
      "news_count": 2
    },
    {
      "ticker": "SPDN",
      "name": "Direxion Daily S&P 500 Bear 1X Shares",
      "predictedPrice": 9.0,
      "actualPrice": 8.99,
      "predictedMove": "+1%",
      "actualMove": "-0.1%",
      "wasCorrect": false,
      "status": "WRONG",
      "confidence": 55,
      "reasoning": "elevated volume, fresh news catalyst",
      "keyFactors": [
        "Gap: 1.6%",
        "Volume: 2.2x",
        "Float: 1000.0M",
        "News: 2"
      ],
      "predictionDate": "2026-06-11",
      "targetDate": "2026-06-11",
      "checkDate": "2026-06-12",
      "priceType": "Pre-Market High (4:00-9:59 AM EST)",
      "gap_percent": 1.6,
      "volume_ratio": 2.2,
      "float": 1000.0,
      "short_percent": 0.0,
      "news_count": 2
    }
  ],
  "lastUpdated": "2026-06-12 01:00 AM",
  "totalPredictions": 90,
  "correctPredictions": 9,
  "accuracy": 10.0,
  "previousAccuracy": 10.0
}